[
  {
    "id": "developer",
    "name": "開発者の道",
    "icon": "💻",
    "tagline": "コードで世界を動かす戦士",
    "description": "GitHub と Azure のクラウドネイティブ開発スキルを段階的に獲得する道。GitHub の基礎から CI/CD、Azure 上のアプリ開発、DevOps まで一貫して積み上げます。",
    "officialUrl": "https://learn.microsoft.com/credentials/browse/?roles=developer",
    "dungeons": [
      {
        "certId": "az-900",
        "name": "Microsoft Azure Fundamentals",
        "url": "https://learn.microsoft.com/credentials/certifications/azure-fundamentals/",
        "note": "クラウドと Azure の基礎概念を身につける入門資格"
      },
      {
        "certId": "gh-100",
        "name": "GitHub Foundations",
        "url": "https://learn.microsoft.com/credentials/certifications/github-foundations/",
        "note": "GitHub の基本機能・コラボレーション・セキュリティの基礎"
      },
      {
        "certId": "gh-200",
        "name": "GitHub Actions",
        "url": "https://learn.microsoft.com/credentials/certifications/github-actions/",
        "note": "ワークフロー自動化と CI/CD パイプライン構築"
      },
      {
        "certId": "az-204",
        "name": "Azure Developer Associate",
        "url": "https://learn.microsoft.com/credentials/certifications/azure-developer/",
        "note": "Azure 上でスケーラブルなアプリと API を設計・実装"
      },
      {
        "certId": "az-400",
        "name": "DevOps Engineer Expert",
        "url": "https://learn.microsoft.com/credentials/certifications/devops-engineer/",
        "note": "ソース管理・CI/CD・リリース戦略を含む DevOps の総合力"
      }
    ]
  },
  {
    "id": "infra",
    "name": "インフラ魔導士の道",
    "icon": "🏰",
    "tagline": "クラウドを支配する守護者",
    "description": "Azure のコア基盤を運用する管理者・アーキテクトを目指す道。基礎から運用・ネットワーク・セキュリティ・アーキテクトへと段階的に昇格します。",
    "officialUrl": "https://learn.microsoft.com/credentials/browse/?roles=administrator%2Csolution-architect",
    "dungeons": [
      {
        "certId": "az-900",
        "name": "Microsoft Azure Fundamentals",
        "url": "https://learn.microsoft.com/credentials/certifications/azure-fundamentals/",
        "note": "クラウドと Azure の基礎"
      },
      {
        "certId": "az-104",
        "name": "Azure Administrator Associate",
        "url": "https://learn.microsoft.com/credentials/certifications/azure-administrator/",
        "note": "ID・ストレージ・コンピュート・ネットワーク・監視の運用"
      },
      {
        "certId": "az-700",
        "name": "Azure Network Engineer Associate",
        "url": "https://learn.microsoft.com/credentials/certifications/azure-network-engineer/",
        "note": "Azure のネットワーク設計と実装"
      },
      {
        "certId": "az-500",
        "name": "Azure Security Engineer Associate",
        "url": "https://learn.microsoft.com/credentials/certifications/azure-security-engineer/",
        "note": "ID・プラットフォーム・データ・アプリのセキュリティ"
      },
      {
        "certId": "az-305",
        "name": "Azure Solutions Architect Expert",
        "url": "https://learn.microsoft.com/credentials/certifications/azure-solutions-architect/",
        "note": "インフラ・アプリ・データを含むエンドツーエンド設計"
      }
    ]
  },
  {
    "id": "ai-engineer",
    "name": "AI賢者の道",
    "icon": "🔮",
    "tagline": "知能を召喚する研究者",
    "description": "Azure の AI / ML サービスを活用する AI エンジニアへの道。基礎から Cognitive Services・Bot・Machine Learning まで、実務適用を段階的に習得します。",
    "officialUrl": "https://learn.microsoft.com/credentials/browse/?roles=ai-engineer%2Cdata-scientist",
    "dungeons": [
      {
        "certId": "az-900",
        "name": "Microsoft Azure Fundamentals",
        "url": "https://learn.microsoft.com/credentials/certifications/azure-fundamentals/",
        "note": "クラウドと Azure の基礎"
      },
      {
        "certId": "ai-900",
        "name": "Microsoft Azure AI Fundamentals",
        "url": "https://learn.microsoft.com/credentials/certifications/azure-ai-fundamentals/",
        "note": "AI ワークロードと Azure AI サービスの基礎"
      },
      {
        "certId": "ai-102",
        "name": "Azure AI Engineer Associate",
        "url": "https://learn.microsoft.com/credentials/certifications/azure-ai-engineer/",
        "note": "Cognitive Services・Azure AI Search・Bot Framework による AI 実装"
      },
      {
        "certId": "dp-100",
        "name": "Azure Data Scientist Associate",
        "url": "https://learn.microsoft.com/credentials/certifications/azure-data-scientist/",
        "note": "Azure Machine Learning での ML モデル設計と運用"
      }
    ]
  }
]
